jsonj/JsonJ.py
jsonj/__init__.py
JsonJ-0.1.6.dist-info/LICENSE.txt
JsonJ-0.1.6.dist-info/METADATA
JsonJ-0.1.6.dist-info/WHEEL
JsonJ-0.1.6.dist-info/top_level.txt
JsonJ-0.1.6.dist-info/RECORD
