Metadata-Version: 2.1
Name: JsonJ
Version: 0.1.6
Summary: A library to prase Json Tree data in-order to make things simpler
Home-page: https://github.com/Joish/JsonParser
Author: Joish J Bosco
Author-email: joishbosco99@gmail.com
License: MIT
Download-URL: https://github.com/Joish/JsonJ/archive/v_0.1.6.tar.gz
Keywords: Python 3,Json,Tree,Tree Traversal,Recursive
Platform: UNKNOWN
Classifier: Development Status :: 3 - Alpha
Classifier: Intended Audience :: Developers
Classifier: Topic :: Software Development :: Build Tools
Classifier: License :: OSI Approved :: MIT License
Classifier: Programming Language :: Python :: 3
Classifier: Programming Language :: Python :: 3.4
Classifier: Programming Language :: Python :: 3.5
Classifier: Programming Language :: Python :: 3.6
Classifier: Programming Language :: Python :: 3.7
